embeddr/cli.py
embeddr/py.typed
embeddr/api/__init__.py
embeddr/api/routes.py
embeddr/api/endpoints/__init__.py
embeddr/api/endpoints/collections.py
embeddr/api/endpoints/images.py
embeddr/api/endpoints/jobs.py
embeddr/api/endpoints/system.py
embeddr/api/endpoints/workspace.py
embeddr/commands/config.py
embeddr/commands/serve.py
embeddr/core/config.py
embeddr/core/logging_utils.py
embeddr/core/project.py
embeddr/db/__init__.py
embeddr/db/session.py
embeddr/mcp/__init__.py
embeddr/mcp/server.py
embeddr/scripts/create_tables.py
embeddr/web/embeddr_logo_transparent.webp
embeddr/web/favicon.ico
embeddr/web/favicon_dev.ico
embeddr/web/index.html
embeddr/web/manifest.json
embeddr/web/robots.txt
embeddr/web/assets/ComingSoonPage-BRD-eoOI.js
embeddr/web/assets/docs-B5NN-tl5.js
embeddr/web/assets/index-C0xEQQ8B.js
embeddr/web/assets/index-C1usikAF.css
embeddr/web/assets/index-CMRn3KU4.js
embeddr/web/assets/jetbrains-mono-cyrillic-wght-normal-D73BlboJ.woff2
embeddr/web/assets/jetbrains-mono-greek-wght-normal-Bw9x6K1M.woff2
embeddr/web/assets/jetbrains-mono-latin-ext-wght-normal-DBQx-q_a.woff2
embeddr/web/assets/jetbrains-mono-latin-wght-normal-B9CIFXIH.woff2
embeddr/web/assets/jetbrains-mono-vietnamese-wght-normal-Bt-aOZkq.woff2
embeddr/web/assets/settings-CMve1TG4.js
embeddr/web/assets/umap-BS34B9Du.js
embeddr/web/assets/useSettings-D9uWDXCy.js
embeddr_cli-0.1.3.dist-info/licenses/LICENSE.md
embeddr_cli-0.1.3.dist-info/METADATA
embeddr_cli-0.1.3.dist-info/WHEEL
embeddr_cli-0.1.3.dist-info/entry_points.txt
embeddr_cli-0.1.3.dist-info/top_level.txt
embeddr_cli-0.1.3.dist-info/RECORD
