Metadata-Version: 2.4
Name: embeddr-cli
Version: 0.1.3
Summary: Embeddr Local CLI Application
Project-URL: Homepage, https://github.com/embeddr-net/embeddr-cli
Project-URL: Repository, https://github.com/embeddr-net/embeddr-cli
Project-URL: Issues, https://github.com/embeddr-net/embeddr-cli/issues
Requires-Python: >=3.12
License-File: LICENSE.md
Requires-Dist: fastapi[standard]>=0.128.0
Requires-Dist: numpy>=2.4.0
Requires-Dist: pillow>=12.0.0
Requires-Dist: pydantic-settings>=2.12.0
Requires-Dist: python-multipart>=0.0.21
Requires-Dist: sqlmodel>=0.0.29
Requires-Dist: transformers>=4.57.3
Requires-Dist: typer>=0.21.0
Requires-Dist: uvicorn>=0.40.0
Requires-Dist: embeddr-core>=0.1.4
Requires-Dist: fastmcp>=2.14.1
Provides-Extra: torch
Requires-Dist: torch>=2.9; extra == "torch"
Dynamic: license-file
